readme_docstring/__init__.py
readme_docstring/classes.py
readme_docstring/functions.py
readme_docstring-2019.4.2.dist-info/METADATA
readme_docstring-2019.4.2.dist-info/WHEEL
readme_docstring-2019.4.2.dist-info/top_level.txt
readme_docstring-2019.4.2.dist-info/RECORD
