Metadata-Version: 2.1
Name: readme-docstring
Version: 2019.4.2
Summary: generate README from python docstrings
Home-page: https://github.com/looking-for-a-job/readme-docstring.py
License: UNKNOWN
Keywords: readme docstring
Platform: UNKNOWN
Classifier: License :: Public Domain
Classifier: Operating System :: OS Independent
Classifier: Programming Language :: Python
Classifier: Programming Language :: Python :: 2
Classifier: Programming Language :: Python :: 2.7
Classifier: Programming Language :: Python :: 3
Classifier: Programming Language :: Python :: 3.4
Classifier: Programming Language :: Python :: 3.5
Classifier: Programming Language :: Python :: 3.6
Classifier: Programming Language :: Python :: 3.7
Classifier: Topic :: Software Development
Requires-Dist: click
Requires-Dist: markdown-table
Requires-Dist: public
Requires-Dist: setupcfg
Requires-Dist: setuptools
